MANIFEST.in
README.md
requirements.txt
setup.py
async_scheduler/__init__.py
async_scheduler/scheduler.py
async_scheduler.egg-info/PKG-INFO
async_scheduler.egg-info/SOURCES.txt
async_scheduler.egg-info/dependency_links.txt
async_scheduler.egg-info/not-zip-safe
async_scheduler.egg-info/requires.txt
async_scheduler.egg-info/top_level.txt
demo/main.py