Metadata-Version: 1.1
Name: async-scheduler
Version: 0.0.3
Summary: Асинхронный планировщик задач
Home-page: https://bitbucket.org/igor_kovalenko/async_scheduler
Author: Kovalenko Igor
Author-email: kovalenko.s.igor@gmail.com
License: BSD
Platform: any
Classifier: Environment :: Web Environment
Classifier: Intended Audience :: Developers
Classifier: License :: OSI Approved :: BSD License
Classifier: Operating System :: OS Independent
Classifier: Programming Language :: Python
Classifier: Topic :: Internet :: WWW/HTTP :: Dynamic Content
Classifier: Topic :: Software Development :: Libraries :: Python Modules
